Metadata-Version: 2.1
Name: BMESBIO2Data
Version: 0.0.0.3
Summary: Terry toolkit BMESBIO2Data
Home-page: https://www.terrychan.org/BMESBIO2Data/
Author: Terry Chan
Author-email: napoler2008@gmail.com
License: UNKNOWN
Platform: UNKNOWN
